pybrowser/__init__.py
pybrowser/api.py
pybrowser/common_utils.py
pybrowser/constants.py
pybrowser/decorators.py
pybrowser/downloader.py
pybrowser/driver_handler.py
pybrowser/exceptions.py
pybrowser/htmlm.py
pybrowser/listeners.py
pybrowser/log_adapter.py
pybrowser/requester.py
pybrowser/elements/__init__.py
pybrowser/elements/actions.py
pybrowser/elements/button.py
pybrowser/elements/checkbox.py
pybrowser/elements/element.py
pybrowser/elements/file.py
pybrowser/elements/form.py
pybrowser/elements/input.py
pybrowser/elements/link.py
pybrowser/elements/radio.py
pybrowser/elements/select.py
pybrowser/elements/utils.py
pybrowser/external/htmlrenderer.py
pybrowser/external/parse.py
pybrowser/external/utils.py
get_pybrowser-0.2.0.dist-info/LICENSE
get_pybrowser-0.2.0.dist-info/METADATA
get_pybrowser-0.2.0.dist-info/WHEEL
get_pybrowser-0.2.0.dist-info/top_level.txt
get_pybrowser-0.2.0.dist-info/RECORD
