Metadata-Version: 2.1
Name: get-pybrowser
Version: 0.2.0
Summary: Selenium based, user friendly Browser Automation API
Home-page: https://github.com/abranjith/pybrowser
Author: ranjith
Author-email: abranjith@gmail.com
License: MIT
Platform: UNKNOWN
Classifier: License :: OSI Approved :: MIT License
Classifier: Programming Language :: Python
Classifier: Programming Language :: Python :: 3.7
Classifier: Programming Language :: Python :: Implementation :: CPython
Classifier: Programming Language :: Python :: Implementation :: PyPy
Requires-Python: >=3.7.0
Requires-Dist: requests
Requires-Dist: selenium (==3.141.0)
Requires-Dist: pyquery (==1.4.0)
Requires-Dist: pyppeteer (==0.0.25)
